{
  "notification": "",
  "products": [
    {
      "uuid": "55855976-6cab-4539-8ea3-dc087f60ef71",
      "title": "101 AI Abstract Logo (Gambar + Prompt)",
      "url": "https://lynk.id/agungsundoro/xrygwjre685k",
      "coverImage": "https://cdn.lynkid.my.id/products/25-06-2026/1782383371130_4203796.webp"
    },
    {
      "uuid": "05439eaa-0c57-41ca-99f8-aaaa3a90f633",
      "title": "101 AI Emblem Logo (Gambar + Prompt)",
      "url": "https://lynk.id/agungsundoro/rv9jp3go9g7k",
      "coverImage": "https://cdn.lynkid.my.id/products/25-06-2026/1782366328843_9190352.webp"
    },
    {
      "uuid": "15b11ef6-1cdc-4481-8356-74052323e095",
      "title": "101 AI Letterform Logo (Gambar + Prompt)",
      "url": "https://lynk.id/agungsundoro/59n1vj58296g",
      "coverImage": "https://cdn.lynkid.my.id/products/25-06-2026/1782346844311_3471296.webp"
    },
    {
      "uuid": "68c7d1fa-0877-47ac-ae8d-2b1ec49f4a56",
      "title": "101 AI Mascot Logo (Gambar + Prompt)",
      "url": "https://lynk.id/agungsundoro/9kol0o3v4jg6",
      "coverImage": "https://cdn.lynkid.my.id/products/25-06-2026/1782385961230_6289454.webp"
    },
    {
      "uuid": "d27bf806-6984-430e-9c46-96332441675e",
      "title": "101 AI Pictorial Logo (Gambar + Prompt)",
      "url": "https://lynk.id/agungsundoro/5z4r8mymm3yr",
      "coverImage": "https://cdn.lynkid.my.id/products/25-06-2026/1782352325161_4378130.webp"
    },
    {
      "uuid": "2e894352-2da8-4aea-a545-934661032d7f",
      "title": "101 AI Wordmark Logo (Gambar + Prompt)",
      "url": "https://lynk.id/agungsundoro/ndx9q17vwq0e",
      "coverImage": "https://cdn.lynkid.my.id/products/25-06-2026/1782373202581_3412119.webp"
    },
    {
      "uuid": "b88822b4-aa14-4560-acde-3df38e3745cd",
      "title": "196 AI Avatar Pria (Gambar + Prompt)",
      "url": "https://lynk.id/agungsundoro/wpyqezl5m26w",
      "coverImage": "https://cdn.lynkid.my.id/products/26-06-2026/1782440268231_4090763.webp"
    },
    {
      "uuid": "a0ad593a-3d6c-4097-b115-aa4e9f119558",
      "title": "196 AI Avatar Wanita (Gambar + Prompt)",
      "url": "https://lynk.id/agungsundoro/5647x2g7gxnm",
      "coverImage": "https://cdn.lynkid.my.id/products/26-06-2026/1782442947323_2949027.webp"
    },
    {
      "uuid": "49289a97-516c-4f4d-bb44-50a299682154",
      "title": "217 Pahlawan Indonesia versi AI 3D Pixar (Gambar + Prompt)",
      "url": "https://lynk.id/agungsundoro/8vw676dv519x",
      "coverImage": "https://cdn.lynkid.my.id/products/29-06-2026/1782691935811_6309155.webp"
    },
    {
      "uuid": "778ab169-7341-48d4-bc8c-09943dd28a7f",
      "title": "25,000+ Prompts untuk Copywriting",
      "url": "https://lynk.id/agungsundoro/o2wzv7qd0gk3",
      "coverImage": "https://cdn.lynkid.my.id/products/30-06-2026/1782780056845_4726474.webp"
    },
    {
      "uuid": "6589e2bb-d39e-4e16-a80f-f65a8297d2bb",
      "title": "300+ AI Poster Makanan (Gambar + Prompt)",
      "url": "https://lynk.id/agungsundoro/0zrqzg212r6g",
      "coverImage": "https://cdn.lynkid.my.id/products/23-06-2026/1782214934601_8167591.webp"
    },
    {
      "uuid": "74e9cdf5-7e75-41cd-9dd7-f5a20fa5f7f0",
      "title": "300+ AI Poster Minuman (Gambar + Prompt)",
      "url": "https://lynk.id/agungsundoro/yn84y041rgok",
      "coverImage": "https://cdn.lynkid.my.id/products/24-06-2026/1782318041440_6703469.webp"
    },
    {
      "uuid": "7301a31b-4d6c-4eeb-b399-6c2930f72ed4",
      "title": "99 Profesi AI Avatar (Gambar + Prompt)",
      "url": "https://lynk.id/agungsundoro/w1rw2n5v103z",
      "coverImage": "https://cdn.lynkid.my.id/products/26-06-2026/1782453414884_4213381.webp"
    },
    {
      "uuid": "37f078e6-14de-4d37-8898-e7cde41c2c31",
      "title": "Ad Creative Planner : Rahasia AI Bikin 10 Ide Iklan Meta yang Bikin Orang Klik dalam 5 Menit ⏱️",
      "url": "http://lynk.id/agungsundoro/d8d4pge7pr27",
      "coverImage": "https://cdn.lynkid.my.id/products/08-07-2026/1783477525025_5741610.webp"
    },
    {
      "uuid": "5be8b4a3-580b-4b7e-9f71-6fc6b7ae181c",
      "title": "AI Arts Bundle (300+ AI Prompts + 3,000+ AI Images)",
      "url": "http://lynk.id/agungsundoro/w5w457o9mj4g",
      "coverImage": "https://cdn.lynkid.my.id/products/24-06-2026/1782267494571_7562333.webp"
    },
    {
      "uuid": "75e6a500-5df0-408b-856d-99c68f81c24c",
      "title": "AI Pakaian Pria (Gambar + Prompt)",
      "url": "https://lynk.id/agungsundoro/ox2yvwzx2v0g",
      "coverImage": "https://cdn.lynkid.my.id/products/29-06-2026/1782700927393_3303438.webp"
    },
    {
      "uuid": "2c4372dc-95f1-4964-bc29-1d8a84e6b080",
      "title": "AI Pakaian Wanita (Gambar + Prompt)",
      "url": "https://lynk.id/agungsundoro/v1zer6en4xz4",
      "coverImage": "https://cdn.lynkid.my.id/products/29-06-2026/1782703176355_7588319.webp"
    },
    {
      "uuid": "6df244a5-e9b9-4d2a-8321-8c67a8eb3469",
      "title": "Carousel Ad Maker : Senjata Bikin Iklan Carousel High-Conversion Pake AI 🎨💰",
      "url": "http://lynk.id/agungsundoro/117gyxr78184",
      "coverImage": "https://cdn.lynkid.my.id/products/01-07-2026/1782865499477_6667397.webp"
    },
    {
      "uuid": "283a3d58-0cf7-4d39-82b4-6c39bd273ad4",
      "title": "ClipMotive: AI-Powered Viral Video Clipper (1 Bulan)",
      "url": "https://lynk.id/agungsundoro/de6lqjqe6elw",
      "coverImage": "https://cdn.lynkid.my.id/products/24-06-2026/1782303474078_2489472.webp"
    },
    {
      "uuid": "e69e0fa2-a18c-4570-aede-2c2c6f85f09d",
      "title": "Debate Maker : Panduan Bikin Konten Viral yang Memancing Komentar 💬📈",
      "url": "http://lynk.id/agungsundoro/o9dyown72kgw",
      "coverImage": "https://cdn.lynkid.my.id/products/03-07-2026/1783048060467_4867905.webp"
    },
    {
      "uuid": "32cf5c3b-8464-4b80-a98d-9377ea63dde0",
      "title": "Kreasi AI : Cuan Gila-Gilaan dari Konten, Iklan, dan Avatar AI!",
      "url": "https://lynk.id/agungsundoro/yq3dooyw9816",
      "coverImage": "https://cdn.lynkid.my.id/products/30-11-2025/1764518417936_8986266.webp"
    },
    {
      "uuid": "d0fb7bf4-52fc-4099-be3c-da74f5104827",
      "title": "Kreator Viral : Blueprint 10 Juta Pertama dalam 30 Hari dari Produk Digital di Bantu AI 🚀💰",
      "url": "https://lynk.id/agungsundoro/481y8x5m02jv",
      "coverImage": "https://cdn.lynkid.my.id/products/10-05-2026/1778419398211_5362452.webp"
    },
    {
      "uuid": "a134364c-df93-4562-8e96-98fcea833c39",
      "title": "Playlist Director : Kurikulum Rahasia 10 Langkah Bikin Konten Binge-Watch🎬🍿",
      "url": "http://lynk.id/agungsundoro/1978wydz1gzk",
      "coverImage": "https://cdn.lynkid.my.id/products/01-07-2026/1782912440194_1453947.webp"
    },
    {
      "uuid": "9ad88c21-a969-4aff-93f0-33513788743f",
      "title": "Script Buddy: Sistem 3 Menit Bikin Skrip Video Viral Tanpa Mikir Keras!",
      "url": "https://lynk.id/agungsundoro/zvlrzp4ovjp3",
      "coverImage": "https://cdn.lynkid.my.id/products/08-06-2026/1780896005155_5491827.webp"
    },
    {
      "uuid": "114cab8c-9494-482a-8c38-c2fc56c999c0",
      "title": "Sinema AI : Kursus Pembuatan Animasi, Iklan, dan Konten Video!",
      "url": "https://lynk.id/agungsundoro/35mxg058em83",
      "coverImage": "https://cdn.lynkid.my.id/products/26-10-2025/1761413522169_8187436.webp"
    },
    {
      "uuid": "2a2bc6a1-ee0f-471f-ba6e-7f39cd3af76b",
      "title": "The Content Alchemist: Sulap 1 Ide Jadi Artikel Kece dalam 5 Menit 🪄",
      "url": "http://lynk.id/agungsundoro/7m30n6evwd1d",
      "coverImage": "https://cdn.lynkid.my.id/products/27-06-2026/1782545095062_1838936.webp"
    },
    {
      "uuid": "b8714101-51c6-4830-9a3b-a626526301fe",
      "title": "Thumbnail Generator Gem - Kursus Kilat Bikin Thumbnail High-CTR Pakai AI 💎✨",
      "url": "http://lynk.id/agungsundoro/en92p0w5mdn4",
      "coverImage": "https://cdn.lynkid.my.id/products/04-07-2026/1783159677159_3130163.webp"
    },
    {
      "uuid": "a7f912a7-db0f-4484-8cbb-9194b85488a5",
      "title": "Viral Calendar : Formula Konten FYP 7 Hari 🗓️",
      "url": "http://lynk.id/agungsundoro/v58k1y71yo49",
      "coverImage": "https://cdn.lynkid.my.id/products/29-06-2026/1782744686247_7527662.webp"
    },
    {
      "uuid": "548ab2fa-2abd-467d-b35f-af188dfa160f",
      "title": "Viral Hook Architect - Formula Bikin 20 Hook Viral dalam 3 Menit Pakai AI 💡🚀",
      "url": "http://lynk.id/agungsundoro/r53k8d2qz2v7",
      "coverImage": "https://cdn.lynkid.my.id/products/02-07-2026/1782969864203_2529015.webp"
    }
  ]
}